realsense_cli/__init__.py
realsense_cli/cli.py
realsense_cli/commands/__init__.py
realsense_cli/commands/config.py
realsense_cli/commands/stream.py
realsense_cli/driver/__init__.py
realsense_cli/driver/mock.py
realsense_cli/driver/realsense.py
realsense_cli/printer.py
realsense_cli/stream_view.py
realsense_cli/types.py
realsense_cli/utils.py
realsense_cli-0.2.0.dist-info/METADATA
realsense_cli-0.2.0.dist-info/WHEEL
realsense_cli-0.2.0.dist-info/entry_points.txt
realsense_cli-0.2.0.dist-info/RECORD
