Metadata-Version: 2.1
Name: realsense-cli
Version: 0.2.0
Summary: 
Author: Yehuda Garti
Author-email: yeudag@gmail.com
Requires-Python: >=3.10,<4.0
Classifier: Programming Language :: Python :: 3
Classifier: Programming Language :: Python :: 3.10
Classifier: Programming Language :: Python :: 3.11
Classifier: Programming Language :: Python :: 3.12
Requires-Dist: loguru (>=0.7.0,<0.8.0)
Requires-Dist: pyrealsense2 (>=2.54.1,<3.0.0)
Requires-Dist: typer[all] (>=0.9.0,<0.10.0)
